[
  {
    "id": "e1",
    "from": "Alice <alice@example.com>",
    "to": "demo@demo.com",
    "cc": [],
    "subject": "Welcome to the project",
    "receivedAt": "2025-11-19T09:12:00Z",
    "body": "<p>Hi there,</p><p>Welcome aboard. Let me know if you need anything.</p>",
    "attachments": []
  },
  {
    "id": "e2",
    "from": "Bob <bob@example.com>",
    "to": "demo@demo.com",
    "cc": [],
    "subject": "Weekly status update",
    "receivedAt": "2025-11-18T14:30:00Z",
    "body": "<p>Team,</p><p>This week we completed tasks A, B, and C.</p>",
    "attachments": []
  }
]
